artd_order/__init__.py
artd_order/admin.py
artd_order/apps.py
artd_order/models.py
artd_order/signals.py
artd_order/data/__init__.py
artd_order/data/order_delivery_methods.py
artd_order/data/order_status.py
artd_order/locale/en/LC_MESSAGES/django.po
artd_order/locale/es/LC_MESSAGES/django.po
artd_order/management/__init__.py
artd_order/management/commands/__init__.py
artd_order/management/commands/create_base_order_delivery_method.py
artd_order/management/commands/create_order_statuses.py
artd_order/migrations/0001_initial.py
artd_order/migrations/0002_order_external_id_order_source_and_more.py
artd_order/migrations/0003_alter_orderadress_city.py
artd_order/migrations/0004_alter_order_coupon_code.py
artd_order/migrations/0005_orderadress_json_data_orderstatus_json_data_and_more.py
artd_order/migrations/0006_alter_order_json_data_alter_order_order_status_and_more.py
artd_order/migrations/0007_orderpaymentmethod.py
artd_order/migrations/0008_order_order_payment_method.py
artd_order/migrations/0009_order_created_by.py
artd_order/migrations/__init__.py
artd_packages/__init__.py
artd_packages/asgi.py
artd_packages/settings.py
artd_packages/urls.py
artd_packages/wsgi.py
artd_order-1.0.13.dist-info/LICENSE
artd_order-1.0.13.dist-info/METADATA
artd_order-1.0.13.dist-info/WHEEL
artd_order-1.0.13.dist-info/top_level.txt
artd_order-1.0.13.dist-info/RECORD
